tmrwppk/__init__.py
tmrwppk/tmrwppk.py
tmrwppk-0.0.7.dist-info/LICENSE
tmrwppk-0.0.7.dist-info/METADATA
tmrwppk-0.0.7.dist-info/WHEEL
tmrwppk-0.0.7.dist-info/entry_points.txt
tmrwppk-0.0.7.dist-info/top_level.txt
tmrwppk-0.0.7.dist-info/RECORD
