Metadata-Version: 2.1
Name: tmrwppk
Version: 0.0.7
Summary: Tomorrow's Prices Today
Home-page: https://github.com/hobakill/tmrwppk
Author: Nick Hobart
Author-email: nick@hobart.io
License: MIT license
Keywords: tmrwppk
Platform: UNKNOWN
Classifier: Development Status :: 2 - Pre-Alpha
Classifier: Intended Audience :: Developers
Classifier: License :: OSI Approved :: MIT License
Classifier: Natural Language :: English
Classifier: Programming Language :: Python :: 3.5
Classifier: Programming Language :: Python :: 3.6
Classifier: Programming Language :: Python :: 3.7
Requires-Dist: beautifulsoup4
Requires-Dist: arrow
Requires-Dist: requests
